cmem_plugin_reason/__init__.py
cmem_plugin_reason/doc/__init__.py
cmem_plugin_reason/doc/reason_doc.md
cmem_plugin_reason/doc/validate_doc.md
cmem_plugin_reason/file-icons--owl.svg
cmem_plugin_reason/fluent--brain-circuit-24-regular.svg
cmem_plugin_reason/plugin_reason.py
cmem_plugin_reason/plugin_validate.py
cmem_plugin_reason/robot.jar
cmem_plugin_reason/utils.py
cmem_plugin_reason-2.1.1.dist-info/LICENSE
cmem_plugin_reason-2.1.1.dist-info/METADATA
cmem_plugin_reason-2.1.1.dist-info/WHEEL
cmem_plugin_reason-2.1.1.dist-info/RECORD
