Metadata-Version: 2.3
Name: cmem-plugin-reason
Version: 2.1.1
Summary: Perform reasoning tasks and validate OWL consistency.
License: Apache-2.0
Keywords: eccenca Corporate Memory,plugin
Author: eccenca GmbH
Author-email: cmempy-developer@eccenca.com
Requires-Python: >=3.11,<4.0
Classifier: Development Status :: 4 - Beta
Classifier: Environment :: Plugins
Classifier: License :: OSI Approved :: Apache Software License
Classifier: Programming Language :: Python :: 3
Classifier: Programming Language :: Python :: 3.11
Classifier: Programming Language :: Python :: 3.12
Classifier: Programming Language :: Python :: 3.13
Requires-Dist: cmem-plugin-base (>=4.5.0,<5.0.0)
Requires-Dist: defusedxml (>=0.7.1,<0.8.0)
Requires-Dist: inflection (>=0.5.1,<0.6.0)
Requires-Dist: pathvalidate (>=3.2.3,<4.0.0)
Requires-Dist: validators (>=0.34.0,<0.35.0)
Project-URL: Homepage, https://github.com/eccenca/cmem-plugin-reason
